[
  {
    "id": 1,
    "full_name": "Смирнов Алексей Владимирович",
    "position": "Патологоанатом",
    "contact": "+7-999-123-45-67",
    "qualifications": [
      "Высшая категория",
      "Стаж 15 лет"
    ],
    "hire_date": "2025-12-14",
    "status": "активен"
  },
  {
    "id": 2,
    "full_name": "Сематари Грейвмэн Найцтинэйтинайнович",
    "position": "Патологоанатом",
    "contact": "+78326762312",
    "qualifications": [],
    "hire_date": "2025-12-14",
    "status": "уволен"
  },
  {
    "id": 3,
    "full_name": "Бабын Бубын Бубс",
    "position": "Санитар",
    "contact": "вайбер",
    "qualifications": [
      "3 класса образования"
    ],
    "hire_date": "2025-12-14",
    "status": "активен"
  }
]